<!DOCTYPE highlight [
  <!-- Color Palette: Define reusable color names as hex codes.
       These can be used anywhere in this file as &name; references.
       Customize these to match your terminal theme. -->
  <!ENTITY black   "000000">
  <!ENTITY red     "ff623e">  <!-- Warm red-orange -->
  <!ENTITY green   "46ac36">
  <!ENTITY yellow  "FFFF00">
  <!ENTITY blue    "7095db">  <!-- Soft blue -->
  <!ENTITY magenta "ff2aff">
  <!ENTITY cyan    "0EE3D8">
  <!ENTITY white   "FFFFFF">
  <!ENTITY grey    "D0D4D6">
  <!ENTITY purple  "dc6ad8">
  <!ENTITY teal    "3ea4a3">
  <!ENTITY olive   "9c9a26">
  <!ENTITY orange  "ff8700">
]>

<settings>
  <!--
    ProfanityFE Settings File ~~ EXAMPLE CONFIGURATION
    ~~
    THIS IS AN EXAMPLE. Do not use this file directly. Copy it to create
    your own settings file and customize it for your character:

      cp mahtra.xml ~/.profanity.xml

    Then edit ~/.profanity.xml for your terminal size, guild, hunting areas,
    and personal preferences. See USER_GUIDE.md for full documentation.

    Location: ~/.profanity.xml (or pass ..settings..file=PATH)
    Reload:   Type .reload in..game to hot..reload without restarting.

    This file configures:
      1. Color palette   - XML entities for reusable hex color codes (in DOCTYPE above)
      2. Presets          - Colors for game-defined text categories (speech, whispers, etc.)
      3. Highlights       - Regex patterns that colorize matching text
      4. Key bindings     - Keyboard shortcuts for cursor, scrolling, tabs, and commands
      5. Gag patterns     - Regex patterns that suppress (hide) matching text
      6. Perc-transforms  - Text substitutions for the active spells (percWindow) display
      7. Layouts          - Window arrangement definitions

    Highlights and gags use Ruby regex syntax. Colors use 6-digit hex (RRGGBB).
    XML entities (e.g. &red;) are defined in the DOCTYPE block above.
  -->

  <!-- ================================================================
       PRESETS — Colors for game-defined text categories
       ================================================================
       Presets override how the game server's built-in text styles render.
       The 'id' must match a game stream name. Common IDs:
         whisper, speech, roomName, monsterbold, thought, voln, percWindow
  -->
  <preset id='whisper'    fg='&cyan;'/>
  <preset id='links'      fg='5555ff'/>
  <preset id='speech'     fg='&green;'/>
  <preset id='roomName'   fg='&green;'/>
  <preset id='monsterbold' fg='&yellow;'/>
  <preset id='thought'    fg='&cyan;'/>
  <preset id='voln'       fg='&teal;'/>
  <preset id='percWindow' fg='&cyan;'/>

  <!-- ================================================================
       KEY BINDINGS
       ================================================================
       Bind keyboard keys to actions. See USER_GUIDE.md for the full
       list of available key names and actions.

       Format: <key id='KEY_NAME' action='ACTION_NAME'/>
       Macros: <key id='KEY_NAME' macro='text to send\r'/>
         \r = press Enter    \x = clear buffer    \@ = cursor position
  -->

  <!-- Command entry -->
  <key id='enter'     action='send_command'/>
  <key id='up'        action='previous_command'/>
  <key id='down'      action='next_command'/>

  <!-- Cursor movement -->
  <key id='left'       action='cursor_left'/>
  <key id='right'      action='cursor_right'/>
  <key id='ctrl+left'  action='cursor_word_left'/>
  <key id='ctrl+right' action='cursor_word_right'/>
  <key id='shift+home' action='cursor_home'/>
  <key id='shift+end'  action='cursor_end'/>

  <!-- Editing -->
  <key id='backspace' action='cursor_backspace'/>
  <key id='ctrl+h'    action='cursor_backspace'/>
  <key id='ctrl+w'    action='cursor_backspace_word'/>
  <key id='ctrl+u'    action='cursor_kill_line'/>
  <key id='delete'    action='cursor_delete'/>

  <!-- Window scrolling -->
  <key id='tab'            action='switch_current_window'/>
  <key id='page_up'        action='scroll_current_window_up_page'/>
  <key id='page_down'      action='scroll_current_window_down_page'/>
  <key id='alt+page_up'    action='scroll_current_window_up_one'/>
  <key id='alt+page_down'  action='scroll_current_window_down_one'/>

  <!-- Tab switching (for tabbed text windows) -->
  <key id='alt+1'          action='switch_tab_1'/>
  <key id='alt+2'          action='switch_tab_2'/>
  <key id='alt+3'          action='switch_tab_3'/>
  <key id='ctrl+tab'       action='switch_tab'/>
  <key id='ctrl+shift+tab' action='switch_tab_reverse'/>

  <!-- ================================================================
       HIGHLIGHTS — Regex patterns that colorize matching game text
       ================================================================
       Format: <highlight fg='COLOR' [bg='COLOR'] [ul='true']>REGEX</highlight>
       Later highlights take priority over earlier ones for overlapping matches.
  -->

  <!-- ==================== SKILL DISPLAY COLORS ====================
       The EXP command shows skills in this format:
         "Shield Usage:  357 72% mind lock     (34/34)"
          SkillName:     Rank Pct  LearningState (Mindstate/34)

       These patterns color skills by mindstate (learning intensity):
         white   =  0/34  (not learning)
         cyan    =  1-10/34  (dabbling-pondering)
         green   = 11-20/34  (ruminating-concentrating)
         yellow  = 21-30/34  (very focused-riveted)
         orange  = 31-34/34  (nearly locked-mind locked)
         magenta = 1750 ranks, clear — skill is mastered
  -->
  <highlight fg='&white;'>\w+(\s\w+)?:\s+(?!1750)\d+\s(\d{1,2}|100)(?:\.\d{2})?%\s+(\w+)?(\s+)?(\w+)?(\s+)?\(?\[?\s?(0)\/34\)?\]?</highlight>
  <highlight fg='&cyan;'>\w+(\s\w+)?:\s+\d+\s(\d{1,2}|100)(?:\.\d{2})?%\s+(\w+)?(\s+)?(\w+)?(\s+)?\(?\[?(\s?[1-9]|10)\/34\)?\]?</highlight>
  <highlight fg='&green;'>\w+(\s\w+)?:\s+\d+\s(\d{1,2}|100)(?:\.\d{2})?%\s+(\w+)?(\s+)?(\w+)?(\s+)?\(?\[?(1[1-9]|20)\/34\)?\]?</highlight>
  <highlight fg='&yellow;'>\w+(\s\w+)?:\s+\d+\s(\d{1,2}|100)(?:\.\d{2})?%\s+(\w+)?(\s+)?(\w+)?(\s+)?\(?\[?(2[1-9]|30)\/34\)?\]?</highlight>
  <highlight fg='&orange;'>\w+\s?\w*:\s+\d+\s(\d{1,2}|100)(?:\.\d{2})?%\s+(\w+)?(\s+)?(\w+)?(\s+)?\(?\[?(3[1-4])\/34\)?\]?</highlight>
  <highlight fg='&magenta;'>\w+\s*\w*?:\s+1750\s\d+\.?\d*%\s+clear\s+\(0\/34\)</highlight>
  <!-- EXP header and training-related messages -->
  <highlight fg='&cyan;'>SKILL: Rank\/Percent towards next rank\/Amount learning\/Mindstate [Ff]raction</highlight>
  <highlight fg='&yellow;'>^\w+ is next\.$</highlight>

  <!-- ==================== SKILL DECIMAL COLORS ====================
       Alternative display when using decimal mindstate format (0.00 - 9.99):
         white   = 0.00-0.25
         cyan    = 0.26-0.50
         green   = 0.51-1.00
         yellow  = 1.01-1.49
         orange  = 1.50+
  -->
  <highlight fg='&white;'>\w+\s?\w*\s+0\.([0-1][0-9]|2[0-5])</highlight>
  <highlight fg='&cyan;'>\w+\s?\w*\s+0\.(2[6-9]|[3-4][0-9]|50)</highlight>
  <highlight fg='&green;'>\w+\s?\w*\s+(0\.(5[1-9]|[6-9][0-9])|1\.00)</highlight>
  <highlight fg='&yellow;'>\w+\s?\w*\s+1\.(0[1-9]|[1-4][0-9])</highlight>
  <highlight fg='&orange;'>\w+\s?\w*\s+(1\.(5[0-9]|[6-9][0-9])|[2-9]\.[0-9][0-9])</highlight>

  <!-- ==================== ROOM & NAVIGATION ====================== -->
  <highlight fg='&green;'>^(Obvious (exits|paths)|Room (Number|Exits)|Showing all skills with field experience.|Also here):</highlight>
  <highlight fg='&yellow;'>windowless|building</highlight>

  <!-- ==================== INVENTORY & ITEMS ====================== -->
  <highlight fg='&yellow;'>is being worn\.$</highlight>
  <highlight fg='&magenta;'>which is in your inventory\.$</highlight>
  <!-- Personal inventory items — customize with your own gear names -->
  <highlight fg='&yellow;'>swallow|corn maze|fuzzy dice pouch with black cording|wide leather war belt with an agonite-inlaid gargoyle buckle</highlight>
  <!-- NPCs of interest -->
  <highlight fg='&magenta;'>Gortik</highlight>

  <!-- ==================== WEAPONS ================================ -->
  <!-- Common weapon types — highlights weapon names in loot and combat text -->
  <highlight fg='&yellow;'>\b(sipar|shield|arrows?|bolts|jambiya|katar|hhr'ata|spike|(hand|throwing|marauder|morning)?\s?(axe|club|star|dagger|blade)|scimitar|maul|greataxe|((composite|short)\s?|cross|long|latch|stone)?bow|allarh|boomerang|cutlass|hammer|bola|claymore|knife|(night|parry )?stick|sling|mace|(broad|long|bastard\s)?sword|(light\s)?spear|pasabas|foil)\b</highlight>

  <!-- ==================== GEMS =================================== -->
  <highlight fg='&yellow;'>\b(alexandrite|amber|amethyst|carnelian|chalcedony|citrine|coral|diamond(?!-hide)|emerald|garnet|jade|jasper|lazuli|moonstone|onyx|opal|sapphire|spinel|topaz|tourmaline|pearl|turqoise)\b</highlight>

  <!-- ==================== LOCKSMITH BOXES ======================== -->
  <!-- Container types from the locksmith system -->
  <highlight fg='&yellow;'>\b(?:box|caddy|crate|trunk|casket|skippet|chest|coffer|strongbox)\b</highlight>
  <highlight fg='&yellow;'>^Items worn (on|around|like|over|in\/on|as|attached).*:\s\[\d+\/\d+\]</highlight>
  <highlight fg='&yellow;'>Faster HE Trips, expiring</highlight>
  <!-- Registration warnings (boxes registered to someone else) -->
  <highlight fg='&red;'>(?:is registered to someone else|[Uu]nfamiliar marks of registration)</highlight>
  <highlight fg='&red;'>You notice unfamiliar marks of registration upon it\.</highlight>

  <!-- ==================== NOTABLE ITEMS ========================== -->
  <!-- Items worth noticing in the game world -->
  <highlight fg='&yellow;'>\b(pouch|scroll|cambrinth|gwethdesuan|a corn maze ticket|bloodscrip|uthamar)\b</highlight>
  <highlight fg='&yellow;'>(Inspired|Enlightened) Sigil Comprehension</highlight>
  <highlight fg='&yellow;'>\w+'s? name appears on the result board!</highlight>
  <!-- Crafting recipe book names -->
  <highlight fg='&red;'>\b(slim|alfar|warrior|textbook|centipede)\b</highlight>
  <!-- Crafting gem chunks (colored by type for quick identification) -->
  <highlight fg='&red;'>ruby chunk</highlight>
  <highlight fg='&cyan;'>sapphire chunk</highlight>
  <highlight fg='&green;'>onyx chunk</highlight>

  <!-- ==================== CRAFTING =============================== -->
  <!-- Crafting technique/book names -->
  <highlight fg='&magenta;'>Utility Forging|(Exotic|Decorative) Wood (Adornments|Shaping)|(Artificer|Shaper|Weaving|Threadcraft|Fabric) (Theory|Specialization|Acumen)|(Basic|Advanced|Knitted|Proficient|Cloth) (Runestone Creation|(Outfitting|Container|Accessory|Artificing|Fabric|Decorative Wear|Alchemy) (Design|Principles))</highlight>
  <!-- Crafting materials and components -->
  <highlight fg='&magenta;'>\b(agonite|muracite|telothian|tyrium|bloodscrip|inkpot|blade|handle|pommel|haralun|mistwood|kertig|ruby chunk|onyx chunk|sapphire chunk|unembellished ring|platinum chain|mortar|clamps|bellows|svidaw sis instructions|shovel|pliers|bowl|knitting needles|scissors|bone saw|forging mallet|flamewood riste|spike|textbook|shackle|razaksel|iron scimitar|battle axe|warrior's belt|leathers|harness|stonebow|latchbow)\b</highlight>
  <!-- Crafting tools (cyan to distinguish from materials) -->
  <highlight fg='&cyan;'>\b(bellows|mallet|drawknife|knife|pliers|rasp|rod|shaper|tongs|awl|brazier|burin|loop|needles|scissors|slickstone|yardstick|yiamura)\b</highlight>

  <!-- ==================== CHARACTER INFO ========================= -->
  <!-- INFO command field labels -->
  <highlight fg='&green;'>\b(?:Encumbrance|Name|Race|Guild|Gender|Age|Circle|Wealth|Debt|Favors|Encumbrance|Time Development Points|Deaths|Departs|Overall state of mind|Rested EXP Stored|Usable This Cycle|Cycle Refreshes|Total Ranks Displayed|Skills Included|(\w+) Average)\s?:</highlight>

  <!-- ==================== THIEVERY =============================== -->
  <!-- Cooldown notification for burglary attempts -->
  <highlight fg='&magenta;'>^A tingling on the back of your neck draws attention to itself by disappearing, making you believe the heat is off from your last break in\.</highlight>

  <!-- ==================== LICH SCRIPT OUTPUT ===================== -->
  <!-- Color Lich framework and dr-scripts output in red for visibility -->
  <highlight fg='&red;'>^(--- Lich|\[go2):.*</highlight>
  <highlight fg='&red;'>(?:\[custom\/[\w'-]+\])</highlight>
  <!-- Comprehensive list of known dr-scripts script names -->
  <highlight fg='&red;'>^\[(?i)(tome|mdusk|accept-sell|addroom|afk|alchemy|alias|almanac|appraisal|arenawatch|arrows|astrology|athletics|attunement|autocontingency|automap|autostart|avtalia|bankbot|bescort|better-book|boggle_blast|bolts|bonding-rose|bootstrap|buff(other|-watcher)?|bug-grabber|burgle|carve(-bead)?|charge-holy-weapon|checkfavors|chop-wood|circlecheck|clean-(leather|lumber)|cleric-quests|clerk-tools|combat-trainer|commune|coordinator|corn-maze.*|craft|create_remedies|crossing-(repair|training)|crowns|dependency|discern|drinfomon|dusk-labyrinth|echo|edityaml|empathylink|enchant|equipmanager|esp|events|examine|exp-monitor|expreset|faskinner|faux-atmo|favor|feed-cloak|fill-dirt|find-darkbox|find|first-aid|forestry-buddy|forge|gate|gbox|generate-profile|get2|glyph-of-mana|gmoney|go2|gosafe|gpouch|grave-pile|healer|healme|heal-remedy|herb-stock|horse-trainer|hunting-buddy|infomon|inventory-manager|invoke-rune|jail-buddy|join-thieves|journal|kill-counter|lamprey|learned|levelup|lichbot|links|lnet|lockbox|locksmithing|magic-training|makesteel|mapmap|mech-lore|mine|mining-buddy|mining-manager|mm|moonwatch|multi|narost-glass|narost|newbie-gear|new-character|nexus|om|oshu_manor|outdoorsmanship|paladin-quests|pattern-hues|pay-debt|performance|performance-monitor|pick|pilgrimage|playermonitor|play|pray-chadatru|ranger-companion|register|release_cyclic|remedy|repeat|repository|restock|restock-shop|rezz|riverhaven-thieves|roomnumbers|safe-room|sanowret-crystal|schedule|scouting|scroll-search|sell-loot|sell-pouches|setupaliases|sew|shape|shit-list|shockquest|skill-recorder|slackbot|smartlisten|smarttransfer|smash-pumpkins|smash-shells|smelt-deeds|smelt|smith|smoke|sorcery|sorter|spellmonitor|spin|spinner|stabbity|stack-scrolls|status-monitor|steal|study-art|su-helmas|summoning|t2|tarantula|tdps|tendme|tendother|tessera|textsubs|theurgy|tinker|tithe|titlecheck|training-manager|train|transfer-items|truffenyi-commune-quest|ulfhara|update-shops|validate|vanity-pet|vars|wait|walkingastro|wand-watcher|weararmor|weave-cloth|whistle|workorders)(\]|:)?</highlight>

  <!-- ==================== COMMUNICATION ========================== -->
  <highlight fg='&green;'>^\[(LichNet|DRPrime)\]</highlight>
  <highlight fg='&green;'>^\[Private(?:To)?\]</highlight>

  <!-- ==================== COMBAT & TARGETING ===================== -->
  <!-- Player status conditions shown in parentheses after names -->
  <highlight fg='&magenta;'>\((?:calmed|dead|flying|hiding|kneeling|prone|sitting|sleeping|stunned)\)</highlight>
  <!-- Successful targeting/positioning messages -->
  <highlight fg='&magenta;'>^Your formation of a targeting pattern.*|^You leap out of hiding.*|.*position yourself behind.*|.*masterfully position yourself to strike.*|.*best shot possible.*|^You dash forward.*|^Utilizing flawless combat expertise.*|^You feel fully prepared to cast your.*|^Your target pattern has finished forming around the area|^A radiant aura empowers the spell</highlight>
  <!-- Threat warnings -->
  <highlight fg='&yellow;'>.*begins to advance on you.$|[tT]here is nothing in there|^You've gained a new rank in.*$|The groaning sound culminates in a section of wall</highlight>
  <!-- Creature death messages -->
  <highlight fg='&red;'>^An armored warklin crumbles.*|.*a grating bellow.*|^The scout (gurgles|coughs up).*|^The wind hound lets loose.*|^A zombie stomper falls belly-up.*|.*eyes glaze over.*|.*closing its eyes forever.*|.*eyes roll back in its head.*|.*one last time and collapses.*|^A storm bull expires.*</highlight>
  <highlight fg='&red;'>which appears dead</highlight>
  <!-- Coordinate/damage tracking display -->
  <highlight fg='&red;'>\[(k|x|y)\]\-\(\-?\+?\d+\)</highlight>
  <highlight fg='&cyan;'>\[(k|x|y)\]\+\(\+?\-?\d+\)</highlight>

  <!-- ==================== TIMING & ROUNDTIME ===================== -->
  <highlight fg='&red;'>(^\[?Roundtime.*|type: AWAKEN)</highlight>
  <highlight fg='&red;'>^\.\.\.wait \d+ seconds.$</highlight>
  <highlight fg='&white;'>\b(?i)your?\b </highlight>

  <!-- ==================== HEALTH & WOUNDS ======================== -->
  <highlight fg='&red;'>\b(feel a warmth radiate from [^ ]+ touch|feel fully rested|have a brief sensation that leaves your wounds tingling)\.</highlight>
  <!-- Body part names in wound reports -->
  <highlight fg='&yellow;'>\w(abdomen|back|chest|head|skin|nerves|(left|right) (arm|leg|eye|hand)|neck)\w</highlight>
  <!-- Empathic link / wound assessment messages -->
  <highlight fg='&magenta;'>^You sense a successful empathic link.*|^You sense that.*|^The internal (wounds|scars).*|\'s injuries include\.\.\.</highlight>
  <highlight fg='&yellow;'>^Wounds to the [A-Z]+\s?[A-Z]*:</highlight>
  <highlight fg='&purple;'>^The external (wounds|scars).*</highlight>
  <highlight fg='&cyan;'>(\.\.\. no injuries to speak of|\w+ has normal vitality)\.</highlight>
  <!-- Wound severity by rank (1-13 scale, colored by danger level) -->
  <highlight fg='&white;'>-- \w+ \((1|2|3)/13\)</highlight>
  <highlight fg='&cyan;'>-- \w+\s?\w*\s?\w* \((4|5|6)/13\)</highlight>
  <highlight fg='&yellow;'>-- \w+\s?\w* \((7|8|9)/13\)</highlight>
  <highlight fg='&magenta;'>-- \w+\s?\w* \((10|11|12)/13\)</highlight>
  <highlight fg='&red;'>-- \w+ \(13/13\)</highlight>

  <!-- ==================== EMPATHY / SHIFTING ===================== -->
  <!-- Empath racial shifting messages -->
  <highlight fg='&yellow;'>type ACCEPT TRANSFORM</highlight>
  <highlight fg='&magenta;'>.*You turn toward \w+ and notice that \w+ appearance has changed\.|^Inhaling deeply, you close your eyes, focusing intently on reshaping \w+'s? body to your will\.\.\.|^You concentrate on the changes taking place in \w+'s body, guiding it and molding it to your will\.|^Your empathic senses stretch out, forming a link so intense that your breathing slows almost to a stop\.|^You feel the link growing further in strength, demanding all of your thought and concentration\.|^\[Type SHIFT \w+ to begin the transformation.\]|^You bend all your senses to the changes in each particle of \w+\'s body, some growing, some shrinking away, and others changing form and color\.|^Stretching your senses along the link with \w+, you slowly lose the boundary between \w+ and yourself, until you feel the changes moving and shaping as though they were in your own body\.</highlight>
  <highlight fg='&red;'>^You don't feel as if you've sufficiently recovered from the previous shift\.</highlight>
  <highlight fg='&cyan;'>^You feel your ability to Shift return to you\.</highlight>

  <!-- ==================== MAGIC & SPELLS ========================= -->
  <!-- Magic skill mastery names -->
  <highlight fg='&magenta;'>(Augmentation|Debilitation|Targeted|Utility|Warding) Mastery|(Raw|Efficient) (Channeling|Harnessing)|Deep Attunement|Improved Memory|Improvised Rituals|Magic Theorist|Mental Matrices|Sorcerous Patterns|Symbiotic Research</highlight>
  <!-- Active cyclic/Osrel Meraud spell indicators -->
  <highlight fg='&orange;'>\w+\s\((OM|Cyclic)\)</highlight>
  <!-- Spell preparation messages -->
  <highlight fg='&white;'>^You begin chanting a mantra.*|^You trace a.*</highlight>
  <!-- Favor readiness -->
  <highlight fg='&magenta;'>You feel fully prepared to seek assistance from the Immortals once again\.</highlight>
  <!-- Moongate -->
  <highlight fg='&magenta;'>(?i)moongate</highlight>

  <!-- ==================== LOCATIONS & EXPLORATION ================ -->
  <highlight fg='&magenta;'>a volcanic crevasse</highlight>
  <highlight fg='&magenta;'>You also see a subtle trail\.</highlight>
  <!-- Loot bag types -->
  <highlight fg='&magenta;'>\b(?i)(?:(diamond-hide|heavy imperial weave) (?:cloth|leather) loot\w+)\b</highlight>

  <!-- ==================== MISC UI ================================ -->
  <highlight fg='&cyan;'>^Gained:\s.*|almanac</highlight>
  <highlight fg='&magenta;'>^A feeling of shock washes through your veins.*|^A hulking Xala'shar magus glowers darkly at.*</highlight>
  <highlight fg='&yellow;'>rainbow silk prayer tapestry appliqued</highlight>

  <!-- ================================================================
       COMBAT GAG PATTERNS
       ================================================================
       Combat gags suppress text routed to the 'combat' stream only.
       They filter repetitive combat messaging while preserving important
       information like damage taken and health warnings.

       Format: <combat_gag>REGEX</combat_gag>
  -->
  <!-- Keep lines starting with *, [, or < (script output, status, XML) -->
  <combat_gag>^(?!(?:\*|\[|\&lt;))</combat_gag>
  <!-- Hide roundtime in combat stream (shown in countdown bar instead) -->
  <combat_gag>Roundtime</combat_gag>
  <!-- Hide "You reveal" stealth messages in combat -->
  <combat_gag>^You reveal</combat_gag>
  <!-- Hide routine balance/position reports (keep damage warnings) -->
  <combat_gag>You're (?!hurt|beat up|very beat up|badly hurt|very badly hurt|smashed up).* balanced and .* (?:position|advantage)</combat_gag>
  <!-- Hide successful dodge/block messages (you didn't get hit, not important) -->
  <combat_gag>at you\.  You (?:sidestep|dodge|evade|fend|slap|deflect|beat|counter|repulse|(partially|barely)?\s?block|turn|knock)</combat_gag>

  <!-- ================================================================
       GENERAL GAG PATTERNS
       ================================================================
       General gags suppress text from ALL streams. Use these to filter
       repetitive game messaging that clutters the display — creature
       ambient actions, lore book text, equipment visual effects, etc.

       Format: <gag>REGEX</gag>
  -->

  <!-- ==================== YOUR COMBAT ACTIONS ====================
       Hide your own attack verbs (you know what you did) -->
  <gag>&lt; You (?:bash|chop|claw|draw|elbow|feint|fire|gouge|have|jab|kick|lob|lunge|poach|punch|slam|slap|slice|stomp|sweep|swing|thrust)</gag>

  <!-- ==================== OTHER PLAYERS' SPAM ====================
       Nearby players' equipment effects, foraging, item handling, etc. -->
  <gag>^\w+ turns a vardite skeleton key at|^A sharp click emanates from the locking mechanism|^\w+ drops .* into a portable silversteel bucket|from inside (?:his|her) (?:jadeleaf satchel|ankle purse|lotusweave bag|traveler's pack|(?:cloth|leather) loot(?:bag|pouch|sack|belt))|bows \w+ head and chants a mantra|drums \w+ fingers on \w+ bucket rhythmically|(?:roots|forages) around the area|(?:to a strap on|from the straps of) \w+ cotton odaj|^\w+ rummages through|^After a moment, a dull \*THUD\* echoes from within the bucket|^\w+'s feet are (?:soaked|dripping with water)</gag>
  <!-- Other players' equipment notifications -->
  <gag>An unknown substance contained within the vial dangling from your tursa chain glows ominously scarlet|emits a loud \*snap\*\.|^\w+ dripping water everywhere\.|^\w+ gestures\.|^\w+ (?:unties|attaches)|^You decipher the telltale signs of|^The pure golden glow dissipates from|^A pure golden glow enwreathes|^The key writhes in your hand|^\w+ retreats from combat|^You turn a vardite skeleton key at|^\w+ bows (?:his|her) head and chants a (?:prayer|psalm)|^\w+ begins to focus intently around h(?:er|im)self|strikes (?:his|her) heel against the ground</gag>
  <!-- Other players' combat actions -->
  <gag>^\w+ opens (?:his|her) soft gem pouch and quickly fills it with gems|A group of the insects launch themselves at|The studs on your wristcuff flicker, and you feel more battle-ready|The beads on your armband flicker, and you feel more battle-ready\.|^The leaves on your lirisan wristcuff|^Your moonsilver wristcuff briefly shimmers|^The bindings of your bitterweave wristwrap tighten momentarily|^The Imperial dira centered upon your leather armlet shimmers|^\w+ begins to lecture \w+|^A painful lump rises in your throat as some nearby shadows darken</gag>
  <!-- Whisper gags — filter routine healing coordination whispers -->
  <gag>&lt;preset id="whisper"&gt;\w+ whispers,&lt;/preset&gt; "(?:Done!|heal)"$|&lt;preset id="whisper"&gt;You whisper to \w+,&lt;/preset&gt; "(?:heal|Thank you\.)"$</gag>
  <!-- Performance instrument spam (zills, cowbell) from bards -->
  <gag>^\w+ stops playing (?:her|his) song|^\w+ raises (?:her|his) hands skyward, chanting|morgawr bone armband flares with radiant light|^Several of the charms on|^\w+ gets a quiet, peaceful look on \w+ face|jaguar-pelt \w+ flicker briefly</gag>
  <gag>^\w+\s(?:begins?|finishes?).*(?:zills|cowbell).*|^\w+\s(?:gazes? intently into|exhales softly on) \w+ sanowret crystal.*|You hear in your mind a quiet recollection|^You feel fully attuned to the mana streams|^Knowledge from your sanowret crystal</gag>
  <gag>launches into the next verse|on (?:his|her).*cowbell|leans? forward.*(?:zills|cowbell)|^The \w+ comes alive in your hand|^It is mere moments afterward that you feel an itching|bends \w+ head over.*(?:zills|cowbell)|^A soft light blossoms in the very center</gag>
  <gag>(?:crown|thighband) pulses with a soft light|pendant flash white for a moment|shimmer with a strikingly green (?:sheen|hue)|continues? to (?:play|perform).*(?:zills|cowbell)</gag>
  <gag>you continue (?:to (?:play|perform)|playing your.*(?:zills|cowbell))|^You.*(?:play|begin).*(?:zills|cowbell)</gag>
  <!-- Darkbox interaction spam -->
  <gag>\w+ drops some coins into the Darkbox|removes \w+ hand from the Darkbox looking both relieved</gag>

  <!-- ==================== CREATURE AMBIENT ACTIONS ================
       Repetitive creature idle animations and arrival messages.
       Gagging these keeps combat focused on actual hits/damage. -->

  <!-- Generic creature action prefix (catches most creature ambient text) -->
  <gag>^(?:&lt;.*&gt;)?(?:The|A|An) (?:telga orek|ice archon|storm bull|(?:elder )?Adan'f blademaster|(?:bone|adult|young|juvenile) wyvern|jeol moradu|silver-grey cloud rat|(?:fuligin|void-black|shadowfrost)?\s?(?:umbral )?moth|Dragon Priest intercessor)</gag>

  <!-- Jeol moradu (ice golem) ambient and combat flavor text -->
  <gag>begins to advance on a jeol moradu|stops advancing since a jeol moradu is dead|\w+ feints .* at a jeol moradu|&gt;A jeol moradu (?:feints|lunges|slices|thrusts)|The stream of liquid blue-white fire washes over a jeol moradu|^You search the jeol moradu|^Icy blue frost crackles up a jeol moradu|^A jeol moradu (?:roars in frustration|howls in encouragement|walks \w+ with thundering steps|growls out a spell in a thunderous voice|melts away, its remains soaked up by the ground)|^With a thunderous stride, a jeol moradu arrives|^A soft crackle briefly comes from a jeol moradu's direction|^The ground shakes as a jeol moradu thunders in with a blast of frigid air</gag>

  <!-- Storm bull ambient text -->
  <gag>^A storm bull|^A soft crackle briefly comes from a storm bull's direction|^(?:Raising its head, )?(?:[aA]|The) storm bull.*|^(?:Sparks of electricity shimmer around a storm bull's body|Misty tendrils rise from the pale hide of a storm bull|A musical note swells in the air as a storm bull brushes|Horns lowered, a storm bull charges|Shifting from side to side, a storm bull crops)</gag>

  <!-- Ice archon ambient text -->
  <gag>^An ice archon (?:backs away from combat|moves into view|moves ponderously|raises its massive icy foot)|A pile of broken ice slowly loses its shape|A creaking noise of ice scraping against ice|^An ice archon|Appearing to have lost sight of its target, an ice archon stops advancing|climbed (?:down|up) a snow-covered cliff</gag>

  <!-- Wyvern ambient text (bone, adult, young, juvenile variants) -->
  <gag>^Slowly the corpse of a bone wyvern decays into a mass of brittle old bone|^With a ghostly wail a bone wyvern charges into view|^An icy wail cuts through the air as a bone wyvern soars|^You stop advancing because a bone wyvern is dead|^\w+ drops a wyvern claw|^The battle-worn carcass of a \w+ wyvern rots away|^The \w+ wyvern (?:is still a distance away|slowly tips over|'s tail lashes)|^The battered form of a \w+ wyvern slowly decomposes|^Glancing about, an? \w+ wyvern opens its mouth|^With a low growl an? \w+ wyvern skulks|^An? \w+ wyvern (?:snarls loudly|shakes its head|emits a guttural|rakes its black talons|grooms its scales|wakes up|slowly skulks into view|begins to move again|thrashes its leathery-black wings|fluidly leaps to its feet|bounds into view|thrashes its long neck|lurches forward|suddenly draws|hops into view|appears less distracted|draws in a deep breath)|^You can no longer see openings in a young wyvern's defenses|^With its massive leathery-black wings bound in layers|^A gutteral roar cuts through the air as an adult wyvern swoops|^Frozen in place, an adult wyvern's eyes sweep</gag>

  <!-- Umbral moth ambient text -->
  <gag>you notice a fuligin moth trying to|^A nearby shadow darkens and expands, coalescing into a fuligin umbral moth|^The restraints binding a fuligin umbral moth grow soft|is entangled by the encroaching web\.$|^The strong smell of ozone accompanies</gag>

  <!-- Scavenger giant ambient text -->
  <gag>^The scavenger giant begins to incant|^A dark cloud coalesces over the body of the scavenger giant|^A scavenger giant crashes to the ground|^(?:A scavenger giant gestures|A faint breeze surrounds \w+)\.</gag>

  <!-- Crauyarin scuttler ambient text -->
  <gag>^(?:With a slight \*tink!\*, an enriched crauyarin scuttler shatters|A single point of red light expands|Flares of crystalline white luminance bloom|Clear blue light falls about the crauyarin scuttler|Entangling their protuberances, a pair of crauyarin scuttlers|Sudden movement in your peripheral vision reveals a crauyarin scuttler|Your vision skews wildly)|^A crauyarin scuttler (?:swiftly skitters|exchanges semaphoric|glows red and blue)|^(?:The)?\s?(?:Luminous cracks appear|curvature of|Gossamer light skips|A soft crackle briefly comes from|Great zigzag fissures|A hexagonal section of|crystalline white flares|Rearing back,)?\s?(?:[Aa]n enriched)?\s?crauyarin scuttler</gag>

  <!-- ==================== COMBAT FLOW ============================
       Routine combat status messages that add clutter without information -->
  <gag>\[.*(?:overwhelming|dominating) (your)?\s?opponent|^I could not find what you were referring to|^You search the|^You quickly pocket the coins|^You gather up the loot you're interested in|A blazing flame-like droplet lands|^(?:A|The) shimmering ethereal shield|^\w+ manages? to get out of the way of the spinning scythe!|^The scythe swiftly melts away\.|begins to listen to \w+ teach the Scholarship skill</gag>
  <!-- Advancement/range messages -->
  <gag>stops? a .* from advancing any farther|^The .* begins to advance on|closes? to (?:melee|pole weapon) range on|^\w+ assesses (?:his|her) combat situation</gag>
  <gag>closes to pole (?:weapon|melee) range on you!$|^Showing all skills with field experience</gag>
  <!-- Movement/navigation noise -->
  <gag>assumes a \w+ stance, concentrating on something|^The .* lands at \w+('s)? feet|^\w's \w+ lands|^You aren't close enough to attack|^What do you want to advance towards|^(&lt;pushStream id="combat" /&gt;)?(?:A|The) hellish spiral|^You are able to channel all the energy|^The .* absorbs all of the energy|^You are already advancing on|(?:wanders|runs|strolls|goes|drifts|went) (?:north|south|east|west|(?:north|south)east|west|up|down|across)\.$</gag>

  <!-- ==================== SPELL & EQUIPMENT EFFECTS ==============
       Repetitive visual effects from spells, enchanted gear, and familiars -->
  <gag>You feel a chill as a spell breaches your ward\!|^A faint sizzling sound fills the air|^A disturbing black radiance creeps over|^Blood pumping loudly, you whip about in a tumultuous fury|^The \w+ of your wristcuff flicker and you feel more battle-ready|^The nearby shadows swell before an elder Adan|^The chakrel dust upon the surface of your manacle glows|^\s+"?Adan'f (?:lusss|inja)|\w+ with a (?:sharp )?\*crack\*!$|^The taipan tightens its coils about your arm|^You bull-rush at</gag>
  <gag>^The quaking fury inside of you continues unabated|^You struggle to maintain the quaking fury|^The air randomly discharges, leaving behind the scent of ozone|^The air around \w+ begins to crackle with static electricity|^The insects continue to swarm|^\w+ visibly quakes with an inner fury</gag>
  <!-- Wristcuff/equipment visual effects -->
  <gag>^One of the etched patterns upon your frozen-bone wristcuff|^Within the flow of whispered chanting nearby|^The viscous (?:solution drenches|goo burbles)|whirls about in a bold, flashy manner!$|visibly churns with an inner rage!$|^\w+ manages? to remain upright\!|^The castoff flecks fade to black</gag>
  <!-- Lava/fire spell effects (Fire of Ushnish) -->
  <gag>The trickles of (?:silver-grey|blue-white) magma cool|(?:silver-grey|blue-white) lava|then quickly steps forward spinning like a dervish|steps forward and spins</gag>
  <gag>The \w+ lava .* splashes .* burn\.</gag>
  <!-- Pet/familiar periodic messages -->
  <gag>^You notice( as)? a sinewy leopard|^The serpent earcuff coils, sensing your danger|^Your wooden medallion warms in response|^Your purpleheart seed begins to pulsate</gag>
  <!-- Empathy/healing ambient effects -->
  <gag>(?:sprawls|slumps) wearily(?:and (?:passes out|drops like a rock), (?:dead to the world|having yielded to your lullaby))?\.$|^You sense deep traces of empathic shock within|^The molten Life flowing in your blood quickens you|^You feel the warmth in your flesh gradually subside|^EXP HELP for more information</gag>
  <!-- Equipment armor/shield ambient messages -->
  <gag>^Your (?:shield|(?:chain )?hauberk) \w+|^(?:A|The) blue-dappled prereni</gag>
  <!-- Vengeance ruby / bracelet / anklet periodic messages -->
  <gag>^Tiny vengeance rubies on \w+'s leather armband pulse|^The tiny vengeance rubies scattered across your leather armband|blighted gold bracelet flares with radiant light|a sense of peace and restfulness spreading through you|^Overall state of mind: clear</gag>
  <gag>^One of the planetary discs on your uthamar anklet briefly darkens|^Water drips from your thin-edged zills\.|^A faint breeze surrounds it|and is closing steadily\.$</gag>
  <!-- Moon accessory visual effects -->
  <gag>^(?:A faint trail of gleaming|A trio of|One of the|Sparkles follow the|The).*multihued moons.*right forearm|multihued moons suddenly accelerate their chase|A dull crimson glow radiates from \w+'s wooden medallion</gag>
  <!-- Sanowret crystal interaction messages -->
  <gag>^The light and crystal sound of your sanowret crystal fades|^The spirit of the cheetah surges through your veins|^You exhale softly on your sanowret crystal|^With a \*click\*, your changes snap into place|^You fiddle with the tiny levers and dials|^Delicate phofe flowers slowly drift and swirl</gag>

  <!-- ==================== LORE BOOK TEXT ==========================
       Long-form lore text from reading in-game books. These are
       multi-paragraph dumps that flood the screen. -->
  <!-- Gorbesh religion lore -->
  <gag>^Turning to the next page in your kuwinite codex, you read more about the Gorbesh religion|^Her Domain being Spirit, Orisas is the mightiest|^Orisas' planet is Osec|^The Domain of Sraxaec is Blood|^The God of Life especially favors those wounded|^Master of the Domain of Iron, Tieheq is the fiercest|^It is believed that it was Tieheq that went to Xin'Alaudas|^With her Domain of Fire, Merion is the most favored|^It is Merion that devised the arts of Forging|^Eimeuz controls the Domain of Wood|^Eimeuz is especially fond of the forests|^Possessing the Domain of Storm, Aniek is the cruel Goddess|^While all ships bear seals of Eimeuz|^When the land was covered in cold for all the year|^With her Domain of Clay, Aliesa is the kind goddess|^But, she is a great warrior with the fury of a mother|^Master of the Domain of Mist, Sieben is a fickle|^The following document contains some details on the religion of the Gorbesh|^With his Domain of Bone, Xosiurion is the God of Dragons|^Many legends and stories surround the mythic battle between Xosiurion|^Misiumos is the cold and defiant goddess of the Domain of Ice</gag>
  <!-- Spider/wildling lore -->
  <gag>^Blade spiders inhabit the Undergondola|^Nightweaver, nightreaver, and nightstalker unyns|^The Harawep's Spider and Harawep's Pawn spider are especially|^The tomiek-iguji \("deceit-spider" in Gorbesh\)|^Sacred to Harawep, wildling spiders are a sentient race|^Zynachi \("assassin" in Gamgweth\) spiders are a swamp-dwelling|^While conventional spiders spin silk, elder wildling spiders spin wildlace|^Effectively immortal, wildling spiders live until killed|^Unlike conventional spiders, wildling spiders feed on mana|^Wildling spiders are a long-lived species|^It is the venom of wildling spiders that transforms|^When the Spidersworn speak of themselves|^The Spidersworn follow the goddess Harawep|^Their purpose is to serve, translate, and speak for Harawep's creatures|^Is it possible to know the mind of a spider\?</gag>
  <!-- Mana theory lore -->
  <gag>^Invisible and intangible to untrained senses|^It is spell energy, not mana, that is created|^There are two competing theories for to categorize man|^Each frequency of mana is traditionally arrayed|^Field theory, which is proposed to better explain sorcerous|^Mana, simply, is the basic building block of magic|^While field theorists lack evidence for their model</gag>
  <!-- Magical devices lore -->
  <gag>^(?:Magical devices are, simply, devices that|A popular theory of magical genesis places|The mechanism for devices typically come in two forms|In addition, devices can be characterized as self-powered|There are some practical limits to these devices|Activation of a magical device can range|Due to the nature of mana incompatibility)</gag>
  <!-- Holy magic lore -->
  <gag>^The range of effects that Holy magic can conjure|^\w+ (?:and the clerk share a few words|exchanges some words with the clerk)|^Holy magic is theoretically the oldest form|^Holy magic derives both its name and its power|^Moreso than any other discipline of magic, Holy magicians|^While Holy magic is powered by the activity of the Immortals|^It is fair to say that Holy magic has a moralistic bend|^Despite this discipline's strong connection to the Immortals</gag>
  <!-- Attunement lore -->
  <gag>^Attunement is a descriptive term referring to an individual magician's capacity|^Through guided meditation a nascent magician learns|^The initial process of attunement can take anywhere|^Once attuned, a magician may then concentrate|^Nearly everybody possesses the basic mental|^Fables exist about attunement the same as any other magical</gag>
  <!-- Life magic lore -->
  <gag>^Life magic is perhaps the most mysterious realm|^Despite the name, Life mana is strongly identified|^While sufficient Life magic can accelerate|^Despite this, both the Empaths and Rangers|^Life mana is created by or resonate with|^The history of Life magic is incomplete|^Conspiracy theorists claim that the Empath Guild</gag>
  <!-- Lunar magic lore -->
  <gag>^The youngest of the magical disciplines, Lunar magic's scholarly|^Lunar magic is, befitting the name, strongly affected|^Due to the nature of the forces that Lunar mages use|^Another facet of these forces is that they tend|^This volatility combined with a generally malicious edge|^Archeological evidence proves that a highly advanced form|^Moon Mages specifically derive much of the character</gag>
  <!-- Spider history lore -->
  <gag>^In the year 403, as the Spider was on its way|^In the year 410, Kurmin and his engineers constructed|^Physically and mentally altered, Kurmin babbled|^That brings us to the year 432, when the Spider fell ill|^Will the Spider be able to recover\?</gag>
  <!-- Arena lore -->
  <gag>Named after Willowbrook Mysandanuva'r, the Mysandanuva'r Arena|The Owirvald Arena has smooth stone walls|Sel'hevor Arena contains walls carved with images|Stolnor Arena is nearly ostentatious in design|Tanglefoot Arena is Formed from a myriad|Tuulpon'u Arena has sinuous pillars|Verdegti Arena is littered with refuse|Ansprahv Drensyld sponsors the first arena|Drathrok, the Barbarian teacher known for popularizing|The Olgievi Arena contains deep pits|Waldegrave Arena is marked by snow white walls</gag>

  <!-- ==================== STEALTH & MISC ========================= -->
  <gag>^You feel like your powerful presence has gotten|^You notice \w+ attempting to stealthily|^It would help if you were closer|Your shotel is a little awkward|^You begin to stealthily advance|^However, nothing much else happens, as you lack the concentration</gag>
  <gag>^The strong smell of ozone accompanies</gag>
  <gag>^A thunderous din peals from the</gag>
  <gag>^Appearing to have lost sight of its target</gag>
  <gag>^You're already playing a song</gag>
  <gag>Assuming you mean (?:a|an) \w+ eddy</gag>

  <!-- ================================================================
       PERC-TRANSFORM — Text substitutions for the active spells display
       ================================================================
       These shorten text in the percWindow to fit a narrow sidebar.
       Format: <perc-transform pattern="REGEX" replace="REPLACEMENT"/>
  -->
  <!-- Remove duration unit names (roisaen/roisan) to save space -->
  <perc-transform pattern=" (roisaen|roisan)" replace=""/>
  <!-- Replace "Indefinite" duration with "Cyclic" for clarity -->
  <perc-transform pattern="Indefinite" replace="Cyclic"/>
  <!-- Remove "Khri " prefix from Thief abilities (they're all Khri) -->
  <perc-transform pattern="Khri " replace=""/>

  <!-- ================================================================
       LAYOUT — Window arrangement
       ================================================================
       Defines the screen layout. Dimensions support arithmetic with
       'lines' (terminal height) and 'cols' (terminal width).

       Switch layouts at runtime: .layout <name>
       Trigger resize after terminal change: .resize

       This layout is designed for a wide terminal (160+ columns):

       +..........................+.........+.........+
       |                          | death   | perc    |
       |   Main / Combat / Assess | stream  | Window  |
       |   (tabbed text window)   | (17h)   | (17h)   |
       |                          +.........+.........+
       |                          |   Room Window     |
       |   height: lines 2        |   (16h)           |
       |   width:  2/3 of cols    +.........+.........+
       |                          | chat    | fam/ooc |
       |                          | (6h)    | (17h)   |
       +..#[command input ].......+.........+.........+
       | RT  | L: left  | R: right | S: spell|ST|BL|HP
       +.....+..........+..........+.........+..+..+..+
  -->
  <layout id='default'>
    <!-- Right column: death notices, active spells -->
    <window class='text'       top='0'  left='((cols/3)*2)+1' height='17' width='cols/6' value='death'/>
    <window class='percWindow' top='0'  left='((cols/6)*5)+4' height='17' width='cols/6' value='percWindow'/>

    <!-- Right column: room display -->
    <window class='room' top='17' left='((cols/3)*2)+1' height='16' width='cols/3' title-preset='roomName' creatures-preset='monsterbold'/>

    <!-- Right column: chat and misc streams -->
    <window class='text' top='33' left='((cols/3)*2)+1' height='6'  width='cols/3' value='conversation,talk,whispers,lnet,thoughts' buffer-size='3000' timestamp='true'/>
    <window class='text' top='39' left='((cols/3)*2)+1' height='17' width='cols/3' value='familiar,ooc' buffer-size='1000' timestamp='true'/>

    <!-- Sink: capture and discard atmospherics (weather/ambient text) -->
    <window class='sink' value='atmospherics'/>

    <!-- Left column: main game text with tabs for combat/assess -->
    <window class='tabbed' top='0' left='0' height='lines-2' width='(cols/3)*2' tabs='main,combat,assess' buffer-size='10000'/>

    <!-- Status bar (second-to-last row): command input + room players -->
    <window class='indicator' top='lines-2' left='105' height='1' width='(cols - 105)' value='room players' fg='&grey;,&cyan;'/>
    <window class='indicator' top='lines-2' left='0'   width='1'   height='1' label='#' fg='&white;'/>
    <window class='command'   top='lines-2' left='1'   width='104' height='1'/>

    <!-- Bottom row: timers, hand contents, spell prep, vitals -->
    <window class='countdown' top='lines-1' left='0'   width='10' height='1' label='' value='roundtime' fg='&white;,&white;,&white;,&white;' bg='nil,&red;,&blue;'/>

    <window class='indicator' top='lines-1' left='17'  height='1' width='3'  label='L:' fg='&blue;'/>
    <window class='indicator' top='lines-1' left='20'  height='1' width='20' label=' '  value='left'  fg='&white;,&purple;'/>

    <window class='indicator' top='lines-1' left='42'  height='1' width='3'  label='R:' fg='&blue;'/>
    <window class='indicator' top='lines-1' left='45'  height='1' width='20' label=' '  value='right' fg='&white;,&purple;'/>

    <window class='indicator' top='lines-1' left='67'  height='1' width='3'  label='S:' fg='&blue;'/>
    <window class='indicator' top='lines-1' left='70'  height='1' width='25' label=' '  value='spell' fg='&white;,&purple;'/>

    <window class='indicator' top='lines-1' left='96'  height='1' width='4'  label='STUN' value='stunned'  fg='&black;,&yellow;'/>
    <window class='indicator' top='lines-1' left='101' height='1' width='3'  label='BLD'  value='bleeding' fg='&black;,&red;'/>

    <window class='progress'  top='lines-1' left='105' width='3'  height='1' label='' value='health'        fg='&red;,&red;,&red;'       bg='&black;'/>
    <window class='progress'  top='lines-1' left='109' width='3'  height='1' label='' value='mana'          fg='&blue;,&blue;,&blue;'    bg='&black;'/>
    <window class='progress'  top='lines-1' left='113' width='3'  height='1' label='' value='stamina'       fg='&white;,&white;,&white;' bg='&black;'/>
    <window class='progress'  top='lines-1' left='117' width='3'  height='1' label='' value='concentration' fg='&green;,&green;,&green;' bg='&black;'/>
    <window class='progress'  top='lines-1' left='121' width='3'  height='1' label='' value='spirit'        fg='&cyan;,&cyan;,&cyan;'    bg='&black;'/>

    <window class='text'      top='lines-1' left='125' width='33' height='1' value='moonWindow'/>
  </layout>

</settings>
